{
  "rules": [
    {
      "id": 1,
      "keywords": ["你好", "您好", "hi", "hello", "嗨"],
      "response": "您好！👋 我是智能助手，很高兴为您服务。有什么可以帮助您的吗？",
      "priority": 1
    },
    {
      "id": 2,
      "keywords": ["再见", "拜拜", "bye", "goodbye"],
      "response": "再见！👋 期待下次为您服务，祝您生活愉快！",
      "priority": 1
    },
    {
      "id": 3,
      "keywords": ["谢谢", "感谢", "thanks", "thank you"],
      "response": "不客气！😊 很高兴能够帮到您。如果还有其他问题，随时可以问我。",
      "priority": 1
    },
    {
      "id": 4,
      "keywords": ["帮助", "help", "怎么用", "使用说明"],
      "response": "我可以帮您解答各种问题！\n\n📝 使用方法：\n• 直接输入您的问题\n• 我会优先使用预设规则回答\n• 如果规则库没有相关答案，会调用AI大模型\n\n💡 提示：问题描述越清楚，回答越准确哦！",
      "priority": 2
    },
    {
      "id": 5,
      "keywords": ["功能", "能做什么", "capabilities"],
      "response": "我的主要功能包括：\n\n✨ 智能问答\n📚 知识查询\n💬 日常对话\n🔍 信息搜索\n📊 数据分析\n\n我会不断学习进步，为您提供更好的服务！",
      "priority": 2
    },
    {
      "id": 6,
      "keywords": ["时间", "几点", "现在"],
      "response": "当前时间是：" + new Date().toLocaleString('zh-CN', { timeZone: 'Asia/Shanghai' }) + "\n\n⏰ 北京时间（UTC+8）",
      "priority": 1
    },
    {
      "id": 7,
      "keywords": ["天气", "weather"],
      "response": "抱歉，我暂时无法直接查询实时天气信息。\n\n💡 建议：\n• 您可以访问天气预报网站\n• 或使用手机天气应用\n• 具体天气情况请告诉我城市名，我可以提供一般性建议",
      "priority": 2
    },
    {
      "id": 8,
      "keywords": ["联系方式", "客服", "人工"],
      "response": "如需人工客服帮助：\n\n📞 客服热线：400-XXX-XXXX\n📧 邮箱：support@example.com\n⏰ 服务时间：9:00-18:00（工作日）\n\n我会继续努力为您提供帮助！",
      "priority": 2
    },
    {
      "id": 9,
      "keywords": ["价格", "费用", "收费", "多少钱"],
      "response": "关于价格和费用问题：\n\n💰 本服务当前免费使用\n📋 详细价格信息请咨询客服\n🎁 新用户可能有特别优惠\n\n具体收费政策可能会调整，建议关注官方公告。",
      "priority": 2
    },
    {
      "id": 10,
      "keywords": ["bug", "错误", "问题", "不工作"],
      "response": "很抱歉给您带来不便！🙏\n\n请您描述遇到的具体问题：\n• 什么时候出现的？\n• 具体是什么错误？\n• 操作步骤是什么？\n\n我会尽力帮您解决，或转交技术团队处理。",
      "priority": 1
    }
  ]
}
